{"cameraMode":{"drawMode":0,"name":"Shaded","section":"Shading Mode"},"sceneLighting":true,"audioPlay":false,"sceneViewState":{"m_AlwaysRefresh":false,"showFog":true,"showSkybox":true,"showFlares":true,"showImageEffects":true,"showParticleSystems":true,"showVisualEffectGraphs":true,"m_FxEnabled":true},"in2DMode":false,"pivot":{"x":7.659853935241699,"y":-1.9768340587615967,"z":4.0895676612854},"rotation":{"x":-0.11428475379943848,"y":-0.8716512322425842,"z":0.2429424375295639,"w":-0.41011086106300356},"size":10.317449569702149,"orthographic":false}